human_requests/__init__.py
human_requests/fetch.js
human_requests/human_browser.py
human_requests/human_context.py
human_requests/human_page.py
human_requests/human_page.pyi
human_requests/py.typed
human_requests/abstraction/__init__.py
human_requests/abstraction/http.py
human_requests/abstraction/request.py
human_requests/abstraction/response.py
human_requests/fingerprint/__init__.py
human_requests/fingerprint/fingerprint.py
human_requests/fingerprint/fingerprint_gen.html
human_requests/network_analyzer/anomaly_sniffer.py
human_requests-0.1.4.dist-info/licenses/LICENSE
human_requests-0.1.4.dist-info/METADATA
human_requests-0.1.4.dist-info/WHEEL
human_requests-0.1.4.dist-info/top_level.txt
human_requests-0.1.4.dist-info/RECORD
