Metadata-Version: 2.4
Name: human-requests
Version: 0.1.4
Summary: Playwright wrapper обеспечивающий необходимый функционал для человеко-подобного парсинга сайтов
Author-email: Miskler <mail@miskler.ru>
License: MIT License
Project-URL: Homepage, https://github.com/Miskler/human-requests
Project-URL: Repository, https://github.com/Miskler/human-requests
Project-URL: Documentation, https://miskler.github.io/human-requests/basic/quick_start/index.html
Project-URL: Issues, https://github.com/Miskler/human-requests/issues
Classifier: License :: OSI Approved :: MIT License
Classifier: Operating System :: OS Independent
Classifier: Programming Language :: Python :: 3
Classifier: Programming Language :: Python :: 3.10
Classifier: Programming Language :: Python :: 3.11
Classifier: Programming Language :: Python :: 3.12
Classifier: Programming Language :: Python :: 3.13
Classifier: Topic :: Software Development :: Libraries :: Python Modules
Classifier: Topic :: Internet
Classifier: Topic :: Utilities
Requires-Python: >=3.10
License-File: LICENSE
Requires-Dist: ua-parser[regex]
Requires-Dist: playwright
Requires-Dist: selectolax
Dynamic: license-file
